collective/elastic/ingest/__init__.py
collective/elastic/ingest/analysis.py
collective/elastic/ingest/celery.py
collective/elastic/ingest/client.py
collective/elastic/ingest/deleteindex.py
collective/elastic/ingest/elastic.py
collective/elastic/ingest/ingestion.py
collective/elastic/ingest/logging.py
collective/elastic/ingest/mapping.py
collective/elastic/ingest/plone.py
collective/elastic/ingest/plone_test.py
collective/elastic/ingest/postprocessing.py
collective/elastic/ingest/postprocessing_test.py
collective/elastic/ingest/preprocessing.py
collective/elastic/ingest/preprocessing_test.py
collective/elastic/ingest/preprocessings.json
collective/elastic/ingest/removal.py
collective.elastic.ingest-2.1.3.dist-info/LICENSE.GPL
collective.elastic.ingest-2.1.3.dist-info/LICENSE.rst
collective.elastic.ingest-2.1.3.dist-info/METADATA
collective.elastic.ingest-2.1.3.dist-info/WHEEL
collective.elastic.ingest-2.1.3.dist-info/top_level.txt
collective.elastic.ingest-2.1.3.dist-info/RECORD
