Metadata-Version: 2.1
Name: collective.elastic.ingest
Version: 2.1.3
Summary: Ingestion service queue runner between Plone RestAPI and ElasticSearch or OpenSearch.
Author: Katja Süss, Peter Holzer
Author-email: Jens Klein <jk@kleinundpartner.at>
Maintainer-email: Jens Klein <jk@kleinundpartner.at>
License: GPL 2.0
Project-URL: PyPI, https://pypi.python.org/pypi/collective.elastic.ingest
Project-URL: Changelog, https://github.com/collective/collective.elastic.ingest/blob/main/CHANGES.rst
Project-URL: Source, https://github.com/collective/collective.elastic.ingest
Project-URL: Issues, https://github.com/collective/collective.elastic.ingest/issues
Keywords: elasticsearch,opensearch,plone,celery,search,indexer
Classifier: Environment :: Web Environment
Classifier: Framework :: Plone
Classifier: Programming Language :: Python
Classifier: Programming Language :: Python :: 3.8
Classifier: Programming Language :: Python :: 3.9
Classifier: Programming Language :: Python :: 3.10
Classifier: Programming Language :: Python :: 3.11
Classifier: Programming Language :: Python :: 3.12
Classifier: Operating System :: OS Independent
Classifier: License :: OSI Approved :: GNU General Public License v2 (GPLv2)
Classifier: Development Status :: 5 - Production/Stable
Requires-Python: >=3.8
License-File: LICENSE.GPL
License-File: LICENSE.rst
Requires-Dist: CacheControl
Requires-Dist: celery
Requires-Dist: requests
Requires-Dist: setuptools
Provides-Extra: elasticsearch
Requires-Dist: elasticsearch >=8.0 ; extra == 'elasticsearch'
Provides-Extra: opensearch
Requires-Dist: opensearch-py >=2 ; extra == 'opensearch'
Provides-Extra: rabbitmq
Requires-Dist: celery[librabbitmq] ; extra == 'rabbitmq'
Provides-Extra: redis
Requires-Dist: celery[redis] ; extra == 'redis'
Provides-Extra: sentry
Requires-Dist: sentry-sdk ; extra == 'sentry'
Provides-Extra: test
Requires-Dist: pytest ; extra == 'test'
Requires-Dist: requests-mock ; extra == 'test'
Requires-Dist: pdbpp ; extra == 'test'
